{
    "name": "ProductAttributes",
    "fields": [
        {
            "fieldName": "skuType",
            "fieldType": "SkuType",
            "fieldValues": "DEVICE,ACCESSORY,SIM,BOX"
        },
        {
            "fieldName": "shippable",
            "fieldType": "Boolean"
        },
        {
            "fieldName": "createdDate",
            "fieldType": "Instant",
            "fieldValidateRules": [
                "required"
            ]
        },
        {
            "fieldName": "createdBy",
            "fieldType": "String",
            "fieldValidateRules": [
                "required"
            ]
        },
        {
            "fieldName": "lastUpdatedDate",
            "fieldType": "Instant",
            "fieldValidateRules": [
                "required"
            ]
        },
        {
            "fieldName": "lastUpdatedBy",
            "fieldType": "String",
            "fieldValidateRules": [
                "required"
            ]
        },
        {
            "fieldName": "tenantId",
            "fieldType": "String",
            "fieldValidateRules": [
                "required"
            ]
        }
    ],
    "relationships": [],
    "changelogDate": "20200307172200",
    "entityTableName": "product_attributes",
    "dto": "no",
    "pagination": "pagination",
    "service": "serviceClass",
    "jpaMetamodelFiltering": false,
    "fluentMethods": true,
    "readOnly": false,
    "clientRootFolder": "",
    "applications": "*"
}